api/__init__.py
api/cyberArkManager.py
argsparser/__init__.py
argsparser/argsparser.py
constants/__init__.py
constants/runargs.py
src/__init__.py
CyberArk_KeyVault-0.0.2.dist-info/METADATA
CyberArk_KeyVault-0.0.2.dist-info/WHEEL
CyberArk_KeyVault-0.0.2.dist-info/top_level.txt
CyberArk_KeyVault-0.0.2.dist-info/RECORD
