Metadata-Version: 2.1
Name: CyberArk-KeyVault
Version: 0.0.2
Summary: CyberArk python helper function
Author: Ayush Yajnik
Author-email: ayushyajnik1@outlook.com
Requires-Dist: alembic (==1.9.2)
Requires-Dist: bpy (==3.4.0)
Requires-Dist: certifi (==2022.12.7)
Requires-Dist: charset-normalizer (==3.1.0)
Requires-Dist: click (==8.1.3)
Requires-Dist: colorama (==0.4.6)
Requires-Dist: Cython (==0.29.33)
Requires-Dist: distlib (==0.3.4)
Requires-Dist: filelock (==3.7.0)
Requires-Dist: Flask (==2.2.2)
Requires-Dist: Flask-Login (==0.6.2)
Requires-Dist: Flask-Migrate (==4.0.2)
Requires-Dist: Flask-SQLAlchemy (==3.0.2)
Requires-Dist: Flask-WTF (==1.1.1)
Requires-Dist: greenlet (==2.0.1)
Requires-Dist: idna (==3.4)
Requires-Dist: itsdangerous (==2.1.2)
Requires-Dist: Jinja2 (==3.1.2)
Requires-Dist: Mako (==1.2.4)
Requires-Dist: MarkupSafe (==2.1.2)
Requires-Dist: numpy (==1.24.2)
Requires-Dist: platformdirs (==2.5.2)
Requires-Dist: python-dotenv (==0.21.1)
Requires-Dist: requests (==2.28.2)
Requires-Dist: pandas (==1.5.3)
